spotifyoffline/conversion.py
spotifyoffline/credentials.py
spotifyoffline/main.py
spotifyoffline/spotify.py
spotifyoffline/youtube.py
spotifyoffline-0.0.2.dist-info/LICENSE
spotifyoffline-0.0.2.dist-info/METADATA
spotifyoffline-0.0.2.dist-info/WHEEL
spotifyoffline-0.0.2.dist-info/entry_points.txt
spotifyoffline-0.0.2.dist-info/top_level.txt
spotifyoffline-0.0.2.dist-info/RECORD
