Metadata-Version: 2.1
Name: spotifyoffline
Version: 0.0.2
Summary: listen to your favorite spotify songs, offline
Home-page: https://github.com/theaarushgupta/spotifyoffline
Author: Aarush Gupta
Author-email: aarush@theaarushgupta.com
License: AGPLv3+
Platform: UNKNOWN
Classifier: License :: OSI Approved :: GNU Affero General Public License v3 or later (AGPLv3+)
Classifier: Programming Language :: Python :: 3
Classifier: Programming Language :: Python :: 3.8
Requires-Dist: moviepy
Requires-Dist: pytube
Requires-Dist: pyyaml
Requires-Dist: spotipy
